LICENSE
MANIFEST.in
README.md
setup.cfg
setup.py
docs/.gitignore
wagtail_site_sections/__init__.py
wagtail_site_sections/apps.py
wagtail_site_sections/models.py
wagtail_site_sections/serializers.py
wagtail_site_sections.egg-info/PKG-INFO
wagtail_site_sections.egg-info/SOURCES.txt
wagtail_site_sections.egg-info/dependency_links.txt
wagtail_site_sections.egg-info/requires.txt
wagtail_site_sections.egg-info/top_level.txt
wagtail_site_sections/blocks/__init__.py
wagtail_site_sections/blocks/base.py
wagtail_site_sections/blocks/blocks.py
wagtail_site_sections/blocks/material_icons.py
wagtail_site_sections/migrations/0001_initial.py
wagtail_site_sections/migrations/0002_hashes_help_and_updates.py
wagtail_site_sections/migrations/__init__.py
wagtail_site_sections/static/.gitignore
wagtail_site_sections/templates/.gitignore