Metadata-Version: 2.1
Name: wagtail-site-sections
Version: 0.2.0
Summary: Site Sections in Wagtail streamfield
Home-page: https://github.com/thclark/wagtail_site_sections
Author: thclark
Author-email: withheld.find@me.at.github.com
License: MIT
Keywords: wagtail,django,events
Platform: UNKNOWN
Classifier: Development Status :: 4 - Beta
Classifier: Intended Audience :: Developers
Classifier: Topic :: Software Development :: Libraries :: Python Modules
Classifier: License :: OSI Approved :: MIT License
Classifier: Programming Language :: Python :: 3.6
Classifier: Programming Language :: Python :: 3.7
Classifier: Operating System :: OS Independent
